pyap/__init__.py
pyap/address.py
pyap/api.py
pyap/exceptions.py
pyap/parser.py
pyap/py.typed
pyap/source_CA/__init__.py
pyap/source_CA/data.py
pyap/source_GB/__init__.py
pyap/source_GB/data.py
pyap/source_US/__init__.py
pyap/source_US/data.py
pyap/utils.py
pyap2-0.2.0.dist-info/LICENSE
pyap2-0.2.0.dist-info/METADATA
pyap2-0.2.0.dist-info/WHEEL
pyap2-0.2.0.dist-info/RECORD
