Metadata-Version: 2.1
Name: pyap2
Version: 0.2.0
Summary: Pyap2 is a maintained fork of pyap, a regex-based library for parsing US, CA, and UK addresses. The fork adds typing support, handles more address formats and edge cases.
Home-page: https://github.com/argyle-engineering/pyap
License: MIT
Keywords: address,parser,regex
Author: Argyle Developers
Author-email: developers@argyle.io
Requires-Python: >=3.9,<4.0
Classifier: License :: OSI Approved :: MIT License
Classifier: Operating System :: OS Independent
Classifier: Programming Language :: Python :: 3
Classifier: Programming Language :: Python :: 3.9
Classifier: Programming Language :: Python :: 3.10
Classifier: Programming Language :: Python :: 3.11
Classifier: Programming Language :: Python :: 3.10
Classifier: Programming Language :: Python :: 3.11
Classifier: Programming Language :: Python :: 3.9
Classifier: Topic :: Scientific/Engineering :: Information Analysis
Classifier: Topic :: Software Development :: Libraries
Classifier: Topic :: Utilities
Project-URL: Documentation, https://github.com/argyle-engineering/pyap
Project-URL: Repository, https://github.com/argyle-engineering/pyap
